bonk_mcp/__init__.py
bonk_mcp/server.py
bonk_mcp/settings.py
bonk_mcp/utils.py
bonk_mcp/core/letsbonk.py
bonk_mcp/tests/test_ipfs.py
bonk_mcp/tools/__init__.py
bonk_mcp/tools/token_launcher.py
letsbonk_mcp-0.1.4.dist-info/METADATA
letsbonk_mcp-0.1.4.dist-info/WHEEL
letsbonk_mcp-0.1.4.dist-info/entry_points.txt
letsbonk_mcp-0.1.4.dist-info/top_level.txt
letsbonk_mcp-0.1.4.dist-info/RECORD
